{
  "appPageId" : "05ef23d1-b920-4918-ae82-b6437d316503",
  "componentName" : "siteforce:sldsOneColLayout",
  "id" : "7417b1f7-2e03-4577-932a-1ffbc0f2772f",
  "label" : "My Home",
  "regions" : [ {
    "id" : "60738a94-a637-424b-b9df-c2a8cf670f46",
    "regionName" : "header",
    "type" : "region"
  }, {
    "id" : "f1d1d75a-d5b6-4e6d-9362-d240fe0aefbd",
    "regionName" : "content",
    "type" : "region"
  }, {
    "id" : "da6adb4c-7c5e-4dce-ab8b-34865217864d",
    "regionName" : "footer",
    "type" : "region"
  }, {
    "components" : [ {
      "componentAttributes" : {
        "description" : "",
        "metaTags" : "",
        "title" : "My Home"
      },
      "componentName" : "forceCommunity:seoAssistant",
      "id" : "fe71b5fe-e908-4fd1-a51f-eab51a937bee",
      "renditionMap" : { },
      "type" : "component"
    } ],
    "id" : "792e12e2-9c4a-4d81-ad16-b2f563d00173",
    "regionName" : "sfdcHiddenRegion",
    "type" : "region"
  } ],
  "themeLayoutType" : "Inner",
  "type" : "view",
  "viewType" : "custom-my-home"
}